logging_and_error_handling_kit/__init__.py
logging_and_error_handling_kit/error_handler.py
logging_and_error_handling_kit/logger_config.py
logging_and_error_handling_kit-0.1.13.dist-info/licenses/LICENSE
logging_and_error_handling_kit-0.1.13.dist-info/METADATA
logging_and_error_handling_kit-0.1.13.dist-info/WHEEL
logging_and_error_handling_kit-0.1.13.dist-info/top_level.txt
logging_and_error_handling_kit-0.1.13.dist-info/RECORD
