Metadata-Version: 2.4
Name: logging-and-error-handling-kit
Version: 0.1.13
Summary: Env-aware logging with per-call stdout control and a handy ErrorHandler.
Author-email: Omar <onajialhayek@gmail.com>
License: MIT License
Project-URL: Homepage, https://github.com/osintclaude-wq/logging_and_error_handling_kit
Project-URL: Repository, https://github.com/osintclaude-wq/logging_and_error_handling_kit
Project-URL: Issues, https://github.com/osintclaude-wq/logging_and_error_handling_kit/issues
Keywords: logging,error-handling,dotenv
Classifier: Development Status :: 3 - Alpha
Classifier: Intended Audience :: Developers
Classifier: Programming Language :: Python :: 3
Classifier: Programming Language :: Python :: 3.9
Classifier: Programming Language :: Python :: 3.10
Classifier: Programming Language :: Python :: 3.11
Classifier: Programming Language :: Python :: 3.12
Classifier: Operating System :: OS Independent
Requires-Python: >=3.9
License-File: LICENSE
Requires-Dist: python-dotenv<2,>=1.0.0
Requires-Dist: tqdm<5,>=4.66.0
Dynamic: license-file
